dependency_graph.gml
env.yml
environment.yml
excel-dependency-graph.py
finals.py
New Text Document.txt
PKG-INFO
py36.yml
pyproject.toml
README.md
setup.py
excel_dependency_graph-0.1.1.dist-info/METADATA
excel_dependency_graph-0.1.1.dist-info/WHEEL
excel_dependency_graph-0.1.1.dist-info/RECORD
