Metadata-Version: 2.1
Name: excel_dependency_graph
Version: 0.1.1
Summary: A library to parse Excel formulas and create a dependency graph for cells.
Home-page: https://github.com/jiteshgurav/formula-dependency-excel
License: MIT
Author: Jitesh Gurav
Author-email: jpgurav97@gmail.com
Requires-Python: >=3.6,<4.0
Classifier: License :: OSI Approved :: MIT License
Classifier: Programming Language :: Python :: 3
Classifier: Programming Language :: Python :: 3.6
Classifier: Programming Language :: Python :: 3.7
Classifier: Programming Language :: Python :: 3.8
Classifier: Programming Language :: Python :: 3.9
Classifier: Programming Language :: Python :: 3.10
Classifier: Programming Language :: Python :: 3.11
Classifier: Programming Language :: Python :: 3.12
Classifier: Programming Language :: Python :: 3.13
Requires-Dist: matplotlib (>=3.1.0,<4.0.0)
Requires-Dist: networkx (>=2.5,<3.0)
Requires-Dist: openpyxl (>=3.0.0,<4.0.0)
Project-URL: Repository, https://github.com/jiteshgurav/formula-dependency-excel
